epub2audio/__init__.py
epub2audio/_version.py
epub2audio/audio_converter.py
epub2audio/audio_handler.py
epub2audio/config.py
epub2audio/epub2audio.py
epub2audio/epub_processor.py
epub2audio/helpers.py
epub2audio/voices.py
epub2audio-0.5.0.dist-info/METADATA
epub2audio-0.5.0.dist-info/WHEEL
epub2audio-0.5.0.dist-info/entry_points.txt
epub2audio-0.5.0.dist-info/licenses/LICENSE
epub2audio-0.5.0.dist-info/RECORD
