Metadata-Version: 2.4
Name: epub2audio
Version: 0.5.0
Summary: Convert EPUB ebooks to OGG audiobooks with chapter markers
Project-URL: Homepage, https://github.com/clayrosenthal/epub2audio
Project-URL: Repository, https://github.com/clayrosenthal/epub2audio.git
Project-URL: Issues, https://github.com/clayrosenthal/epub2audio/issues
Author-email: Clay Rosenthal <git@mail.clayrosenthal.me>
License-Expression: AGPL-3.0-or-later
License-File: LICENSE
Classifier: Development Status :: 3 - Alpha
Classifier: Intended Audience :: End Users/Desktop
Classifier: License :: OSI Approved :: GNU Affero General Public License v3 or later (AGPLv3+)
Classifier: Operating System :: OS Independent
Classifier: Programming Language :: Python :: 3
Classifier: Programming Language :: Python :: 3.9
Classifier: Programming Language :: Python :: 3.10
Classifier: Programming Language :: Python :: 3.11
Classifier: Programming Language :: Python :: 3.12
Classifier: Topic :: Multimedia :: Sound/Audio :: Conversion
Requires-Python: >=3.10
Requires-Dist: beautifulsoup4>=4.13.3
Requires-Dist: click>=8.1.7
Requires-Dist: ebooklib>=0.18.0
Requires-Dist: kokoro>=0.8.4
Requires-Dist: loguru>=0.7.3
Requires-Dist: markupsafe~=2.1.3
Requires-Dist: mutagen>=1.47.0
Requires-Dist: pydub>=0.25.1
Requires-Dist: roman>=5.0
Requires-Dist: soundfile>=0.12.1
Requires-Dist: torch>=2.6.0
Requires-Dist: torchaudio>=2.6.0
Requires-Dist: tqdm>=4.66.1
Provides-Extra: dev
Requires-Dist: mypy>=1.5.1; extra == 'dev'
Requires-Dist: pytest-cov>=6.0.0; extra == 'dev'
Requires-Dist: pytest>=8.3.4; extra == 'dev'
Requires-Dist: ruff>=0.9.7; extra == 'dev'
